llama_index/__init__.py
llama_index/chat_apps/__init__.py
llama_index/chat_apps/client.py
llama_index/client.py
llama_index/component_definitions/__init__.py
llama_index/component_definitions/client.py
llama_index/core/__init__.py
llama_index/core/api_error.py
llama_index/core/client_wrapper.py
llama_index/core/datetime_utils.py
llama_index/core/file.py
llama_index/core/http_client.py
llama_index/core/jsonable_encoder.py
llama_index/core/pydantic_utilities.py
llama_index/core/query_encoder.py
llama_index/core/remove_none_from_dict.py
llama_index/core/request_options.py
llama_index/core/serialization.py
llama_index/data_sinks/__init__.py
llama_index/data_sinks/client.py
llama_index/data_sinks/types/__init__.py
llama_index/data_sinks/types/data_sink_update_component.py
llama_index/data_sources/__init__.py
llama_index/data_sources/client.py
llama_index/data_sources/types/__init__.py
llama_index/data_sources/types/data_source_update_component.py
llama_index/data_sources/types/data_source_update_custom_metadata_value.py
llama_index/embedding_model_configs/__init__.py
llama_index/embedding_model_configs/client.py
llama_index/embedding_model_configs/types/__init__.py
llama_index/embedding_model_configs/types/embedding_model_config_create_embedding_config.py
llama_index/environment.py
llama_index/errors/__init__.py
llama_index/errors/unprocessable_entity_error.py
llama_index/evals/__init__.py
llama_index/evals/client.py
llama_index/files/__init__.py
llama_index/files/client.py
llama_index/files/types/__init__.py
llama_index/files/types/file_create_from_url_resource_info_value.py
llama_index/files/types/file_create_permission_info_value.py
llama_index/files/types/file_create_resource_info_value.py
llama_index/jobs/__init__.py
llama_index/jobs/client.py
llama_index/llama_extract/__init__.py
llama_index/llama_extract/client.py
llama_index/llama_extract/types/__init__.py
llama_index/llama_extract/types/extract_agent_create_data_schema.py
llama_cloud_sdk-0.0.6.dist-info/METADATA
llama_cloud_sdk-0.0.6.dist-info/WHEEL
llama_cloud_sdk-0.0.6.dist-info/RECORD
